rtsdatetime/__init__.py
rtsdatetime/model.py
rts_datetime-1.1.0.dist-info/METADATA
rts_datetime-1.1.0.dist-info/WHEEL
rts_datetime-1.1.0.dist-info/RECORD
